kamini/__init__.py
kamini/simple.py
pony/__init__.py
pony/simple.py
kamini-0.1.0.dist-info/METADATA
kamini-0.1.0.dist-info/WHEEL
kamini-0.1.0.dist-info/top_level.txt
kamini-0.1.0.dist-info/RECORD
